worldtimebuddy/__init__.py
worldtimebuddy/cli.py
worldtimebuddy/constants.py
worldtimebuddy/utils.py
worldtimebuddy-0.1.3.dist-info/LICENSE
worldtimebuddy-0.1.3.dist-info/METADATA
worldtimebuddy-0.1.3.dist-info/WHEEL
worldtimebuddy-0.1.3.dist-info/entry_points.txt
worldtimebuddy-0.1.3.dist-info/top_level.txt
worldtimebuddy-0.1.3.dist-info/RECORD
