Metadata-Version: 2.1
Name: worldtimebuddy
Version: 0.1.3
Summary: A command-line tool to display current time for different timezones
Home-page: https://github.com/dubesar/worldtimebuddy
Author: Sarvesh Dubey
Author-email: dubeysarvesh5525@gmail.com
Classifier: Programming Language :: Python :: 3
Classifier: License :: OSI Approved :: Apache Software License
Classifier: Operating System :: OS Independent
License-File: LICENSE
Requires-Dist: Click
Requires-Dist: pytz
